{
    "EarthquakeNo": 114077,
    "ReportType": "地震報告",
    "ReportColor": "綠色",
    "ReportContent": "04\/03-02:01花蓮縣秀林鄉發生規模4.9有感地震，最大震度花蓮縣太魯閣、花蓮縣花蓮市、宜蘭縣澳花、南投縣奧萬大3級。",
    "ReportImageURI": "https:\/\/scweb.cwa.gov.tw\/webdata\/OLDEQ\/202504\/2025040302013449077_H.png",
    "ReportRemark": "本報告係中央氣象署地震觀測網即時地震資料地震速報之結果。",
    "Web": "https:\/\/scweb.cwa.gov.tw\/zh-tw\/earthquake\/details\/2025040302013449077",
    "ShakemapImageURI": "https:\/\/scweb.cwa.gov.tw\/webdata\/drawTrace\/plotContour\/2025\/2025077i.png",
    "EarthquakeInfo": {
        "OriginTime": "2025-04-03 02:01:34",
        "Source": "中央氣象署",
        "FocalDepth": 25.3,
        "Epicenter": {
            "Location": "花蓮縣政府北方  19.1  公里 (位於花蓮縣秀林鄉)",
            "EpicenterLatitude": 24.16,
            "EpicenterLongitude": 121.64
        },
        "EarthquakeMagnitude": {
            "MagnitudeType": "芮氏規模",
            "MagnitudeValue": 4.9
        }
    },
    "Intensity": {
        "ShakingArea": [
            {
                "AreaDesc": "南投縣地區",
                "CountyName": "南投縣",
                "InfoStatus": "observe",
                "AreaIntensity": "3級",
                "EqStation": [
                    {
                        "pga": {
                            "unit": "gal",
                            "EWComponent": 6.09,
                            "NSComponent": 6.89,
                            "VComponent": 5.76,
                            "IntScaleValue": 8.13
                        },
                        "pgv": {
                            "unit": "kine",
                            "EWComponent": 0.13,
                            "NSComponent": 0.16,
                            "VComponent": 0.14,
                            "IntScaleValue": 0.2
                        },
                        "StationName": "奧萬大",
                        "StationID": "OWD",
                        "InfoStatus": "observe",
                        "BackAzimuth": 64.01,
                        "EpicenterDistance": 52.54,
                        "SeismicIntensity": "3級",
                        "StationLatitude": 23.955,
                        "StationLongitude": 121.176,
                        "WaveImageURI": "https:\/\/scweb.cwa.gov.tw\/webdata\/drawTrace\/outcome\/2025\/2025077\/3-OWD.gif"
                    },
                    {
                        "pga": {
                            "unit": "gal",
                            "EWComponent": 6.04,
                            "NSComponent": 5.54,
                            "VComponent": 3.08,
                            "IntScaleValue": 6.09
                        },
                        "pgv": {
                            "unit": "kine",
                            "EWComponent": 0.23,
                            "NSComponent": 0.19,
                            "VComponent": 0.15,
                            "IntScaleValue": 0.27
                        },
                        "StationName": "合歡山",
                        "StationID": "WHF",
                        "InfoStatus": "observe",
                        "BackAzimuth": 86.84,
                        "EpicenterDistance": 37.44,
                        "SeismicIntensity": "2級",
                        "StationLatitude": 24.143,
                        "StationLongitude": 121.273,
                        "WaveImageURI": "https:\/\/scweb.cwa.gov.tw\/webdata\/drawTrace\/outcome\/2025\/2025077\/2-WHF.gif"
                    },
                    {
                        "pga": {
                            "unit": "gal",
                            "EWComponent": 1.41,
                            "NSComponent": 0.8,
                            "VComponent": 1.47,
                            "IntScaleValue": 1.65
                        },
                        "pgv": {
                            "unit": "kine",
                            "EWComponent": 0.05,
                            "NSComponent": 0.03,
                            "VComponent": 0.05,
                            "IntScaleValue": 0.07
                        },
                        "StationName": "埔里",
                        "StationID": "WPL",
                        "InfoStatus": "observe",
                        "BackAzimuth": 76.56,
                        "EpicenterDistance": 71.4,
                        "SeismicIntensity": "1級",
                        "StationLatitude": 24.012,
                        "StationLongitude": 120.957,
                        "WaveImageURI": "https:\/\/scweb.cwa.gov.tw\/webdata\/drawTrace\/outcome\/2025\/2025077\/1-WPL.gif"
                    },
                    {
                        "pga": {
                            "unit": "gal",
                            "EWComponent": 0.76,
                            "NSComponent": 1.01,
                            "VComponent": 0.77,
                            "IntScaleValue": 1.04
                        },
                        "pgv": {
                            "unit": "kine",
                            "EWComponent": 0.05,
                            "NSComponent": 0.02,
                            "VComponent": 0.02,
                            "IntScaleValue": 0.05
                        },
                        "StationName": "國姓",
                        "StationID": "WCS",
                        "InfoStatus": "observe",
                        "BackAzimuth": 81.03,
                        "EpicenterDistance": 74.99,
                        "SeismicIntensity": "1級",
                        "StationLatitude": 24.057,
                        "StationLongitude": 120.912,
                        "WaveImageURI": "https:\/\/scweb.cwa.gov.tw\/webdata\/drawTrace\/outcome\/2025\/2025077\/1-WCS.gif"
                    },
                    {
                        "pga": {
                            "unit": "gal",
                            "EWComponent": 1.75,
                            "NSComponent": 1.12,
                            "VComponent": 0.36,
                            "IntScaleValue": 1.76
                        },
                        "pgv": {
                            "unit": "kine",
                            "EWComponent": 0.13,
                            "NSComponent": 0.08,
                            "VComponent": 0.03,
                            "IntScaleValue": 0.14
                        },
                        "StationName": "日月潭",
                        "StationID": "SML",
                        "InfoStatus": "observe",
                        "BackAzimuth": 67.31,
                        "EpicenterDistance": 80.72,
                        "SeismicIntensity": "1級",
                        "StationLatitude": 23.881,
                        "StationLongitude": 120.908,
                        "WaveImageURI": "https:\/\/scweb.cwa.gov.tw\/webdata\/drawTrace\/outcome\/2025\/2025077\/1-SML.gif"
                    },
                    {
                        "pga": {
                            "unit": "gal",
                            "EWComponent": 1.07,
                            "NSComponent": 0.93,
                            "VComponent": 0.55,
                            "IntScaleValue": 1.02
                        },
                        "pgv": {
                            "unit": "kine",
                            "EWComponent": 0.02,
                            "NSComponent": 0.03,
                            "VComponent": 0.01,
                            "IntScaleValue": 0.04
                        },
                        "StationName": "信義鄉",
                        "StationID": "WHY",
                        "InfoStatus": "observe",
                        "BackAzimuth": 57.17,
                        "EpicenterDistance": 95.35,
                        "SeismicIntensity": "1級",
                        "StationLatitude": 23.696,
                        "StationLongitude": 120.853,
                        "WaveImageURI": "https:\/\/scweb.cwa.gov.tw\/webdata\/drawTrace\/outcome\/2025\/2025077\/1-WHY.gif"
                    },
                    {
                        "pga": {
                            "unit": "gal",
                            "EWComponent": 0.57,
                            "NSComponent": 0.93,
                            "VComponent": 0.39,
                            "IntScaleValue": 0.93
                        },
                        "pgv": {
                            "unit": "kine",
                            "EWComponent": 0.03,
                            "NSComponent": 0.04,
                            "VComponent": 0.02,
                            "IntScaleValue": 0.04
                        },
                        "StationName": "竹山",
                        "StationID": "WJS",
                        "InfoStatus": "observe",
                        "BackAzimuth": 67.88,
                        "EpicenterDistance": 100.21,
                        "SeismicIntensity": "1級",
                        "StationLatitude": 23.822,
                        "StationLongitude": 120.728,
                        "WaveImageURI": "https:\/\/scweb.cwa.gov.tw\/webdata\/drawTrace\/outcome\/2025\/2025077\/1-WJS.gif"
                    },
                    {
                        "pga": {
                            "unit": "gal",
                            "EWComponent": 1.04,
                            "NSComponent": 1.23,
                            "VComponent": 1.02,
                            "IntScaleValue": 0.97
                        },
                        "pgv": {
                            "unit": "kine",
                            "EWComponent": 0.04,
                            "NSComponent": 0.04,
                            "VComponent": 0.02,
                            "IntScaleValue": 0.05
                        },
                        "StationName": "名間",
                        "StationID": "WNT",
                        "InfoStatus": "observe",
                        "BackAzimuth": 71.82,
                        "EpicenterDistance": 101.49,
                        "SeismicIntensity": "1級",
                        "StationLatitude": 23.877,
                        "StationLongitude": 120.693,
                        "WaveImageURI": "https:\/\/scweb.cwa.gov.tw\/webdata\/drawTrace\/outcome\/2025\/2025077\/1-WNT.gif"
                    },
                    {
                        "pga": {
                            "unit": "gal",
                            "EWComponent": 0.76,
                            "NSComponent": 0.69,
                            "VComponent": 0.32,
                            "IntScaleValue": 0.82
                        },
                        "pgv": {
                            "unit": "kine",
                            "EWComponent": 0.04,
                            "NSComponent": 0.02,
                            "VComponent": 0.01,
                            "IntScaleValue": 0.04
                        },
                        "StationName": "玉山",
                        "StationID": "YUS",
                        "InfoStatus": "observe",
                        "BackAzimuth": 42.82,
                        "EpicenterDistance": 102.06,
                        "SeismicIntensity": "1級",
                        "StationLatitude": 23.487,
                        "StationLongitude": 120.959,
                        "WaveImageURI": "https:\/\/scweb.cwa.gov.tw\/webdata\/drawTrace\/outcome\/2025\/2025077\/1-YUS.gif"
                    },
                    {
                        "StationName": "魚池",
                        "StationID": "TYC",
                        "BackAzimuth": 70.01,
                        "EpicenterDistance": 83.4,
                        "SeismicIntensity": "1級",
                        "StationLatitude": 23.905,
                        "StationLongitude": 120.87
                    }
                ]
            },
            {
                "AreaDesc": "臺北市地區",
                "CountyName": "臺北市",
                "InfoStatus": "observe",
                "AreaIntensity": "1級",
                "EqStation": [
                    {
                        "pga": {
                            "unit": "gal",
                            "EWComponent": 0.75,
                            "NSComponent": 0.89,
                            "VComponent": 0.62,
                            "IntScaleValue": 0.94
                        },
                        "pgv": {
                            "unit": "kine",
                            "EWComponent": 0.06,
                            "NSComponent": 0.05,
                            "VComponent": 0.03,
                            "IntScaleValue": 0.08
                        },
                        "StationName": "臺北市",
                        "StationID": "TAP",
                        "InfoStatus": "observe",
                        "BackAzimuth": 172.49,
                        "EpicenterDistance": 98,
                        "SeismicIntensity": "1級",
                        "StationLatitude": 25.038,
                        "StationLongitude": 121.514,
                        "WaveImageURI": "https:\/\/scweb.cwa.gov.tw\/webdata\/drawTrace\/outcome\/2025\/2025077\/1-TAP.gif"
                    }
                ]
            },
            {
                "AreaDesc": "雲林縣地區",
                "CountyName": "雲林縣",
                "InfoStatus": "observe",
                "AreaIntensity": "1級",
                "EqStation": [
                    {
                        "pga": {
                            "unit": "gal",
                            "EWComponent": 1.08,
                            "NSComponent": 0.94,
                            "VComponent": 0.43,
                            "IntScaleValue": 1.07
                        },
                        "pgv": {
                            "unit": "kine",
                            "EWComponent": 0.04,
                            "NSComponent": 0.05,
                            "VComponent": 0.02,
                            "IntScaleValue": 0.05
                        },
                        "StationName": "草嶺",
                        "StationID": "CHN5",
                        "InfoStatus": "observe",
                        "BackAzimuth": 57.43,
                        "EpicenterDistance": 116.42,
                        "SeismicIntensity": "1級",
                        "StationLatitude": 23.597,
                        "StationLongitude": 120.677,
                        "WaveImageURI": "https:\/\/scweb.cwa.gov.tw\/webdata\/drawTrace\/outcome\/2025\/2025077\/1-CHN5.gif"
                    },
                    {
                        "pga": {
                            "unit": "gal",
                            "EWComponent": 1.53,
                            "NSComponent": 1.23,
                            "VComponent": 0.72,
                            "IntScaleValue": 1.14
                        },
                        "pgv": {
                            "unit": "kine",
                            "EWComponent": 0.05,
                            "NSComponent": 0.05,
                            "VComponent": 0.02,
                            "IntScaleValue": 0.05
                        },
                        "StationName": "古坑",
                        "StationID": "WGK",
                        "InfoStatus": "observe",
                        "BackAzimuth": 64.06,
                        "EpicenterDistance": 121.13,
                        "SeismicIntensity": "1級",
                        "StationLatitude": 23.684,
                        "StationLongitude": 120.57,
                        "WaveImageURI": "https:\/\/scweb.cwa.gov.tw\/webdata\/drawTrace\/outcome\/2025\/2025077\/1-WGK.gif"
                    },
                    {
                        "pga": {
                            "unit": "gal",
                            "EWComponent": 1.8,
                            "NSComponent": 1.33,
                            "VComponent": 1.19,
                            "IntScaleValue": 1.56
                        },
                        "pgv": {
                            "unit": "kine",
                            "EWComponent": 0.06,
                            "NSComponent": 0.04,
                            "VComponent": 0.02,
                            "IntScaleValue": 0.07
                        },
                        "StationName": "西螺",
                        "StationID": "C092",
                        "InfoStatus": "observe",
                        "BackAzimuth": 70.58,
                        "EpicenterDistance": 124.53,
                        "SeismicIntensity": "1級",
                        "StationLatitude": 23.789,
                        "StationLongitude": 120.486,
                        "WaveImageURI": "https:\/\/scweb.cwa.gov.tw\/webdata\/drawTrace\/outcome\/2025\/2025077\/1-C092.gif"
                    },
                    {
                        "pga": {
                            "unit": "gal",
                            "EWComponent": 1.41,
                            "NSComponent": 1.51,
                            "VComponent": 0.87,
                            "IntScaleValue": 1.46
                        },
                        "pgv": {
                            "unit": "kine",
                            "EWComponent": 0.06,
                            "NSComponent": 0.06,
                            "VComponent": 0.02,
                            "IntScaleValue": 0.08
                        },
                        "StationName": "斗六市",
                        "StationID": "WDL",
                        "InfoStatus": "observe",
                        "BackAzimuth": 66.14,
                        "EpicenterDistance": 122.63,
                        "SeismicIntensity": "1級",
                        "StationLatitude": 23.715,
                        "StationLongitude": 120.539,
                        "WaveImageURI": "https:\/\/scweb.cwa.gov.tw\/webdata\/drawTrace\/outcome\/2025\/2025077\/1-WDL.gif"
                    },
                    {
                        "pga": {
                            "unit": "gal",
                            "EWComponent": 1.09,
                            "NSComponent": 0.99,
                            "VComponent": 0.98,
                            "IntScaleValue": 1.11
                        },
                        "pgv": {
                            "unit": "kine",
                            "EWComponent": 0.05,
                            "NSComponent": 0.04,
                            "VComponent": 0.03,
                            "IntScaleValue": 0.05
                        },
                        "StationName": "麥寮",
                        "StationID": "WML",
                        "InfoStatus": "observe",
                        "BackAzimuth": 74.62,
                        "EpicenterDistance": 149.56,
                        "SeismicIntensity": "1級",
                        "StationLatitude": 23.804,
                        "StationLongitude": 120.223,
                        "WaveImageURI": "https:\/\/scweb.cwa.gov.tw\/webdata\/drawTrace\/outcome\/2025\/2025077\/1-WML.gif"
                    },
                    {
                        "pga": {
                            "unit": "gal",
                            "EWComponent": 1.95,
                            "NSComponent": 2.12,
                            "VComponent": 1.27,
                            "IntScaleValue": 1.92
                        },
                        "pgv": {
                            "unit": "kine",
                            "EWComponent": 0.08,
                            "NSComponent": 0.06,
                            "VComponent": 0.03,
                            "IntScaleValue": 0.08
                        },
                        "StationName": "四湖",
                        "StationID": "WSF",
                        "InfoStatus": "observe",
                        "BackAzimuth": 67.9,
                        "EpicenterDistance": 155.01,
                        "SeismicIntensity": "1級",
                        "StationLatitude": 23.636,
                        "StationLongitude": 120.23,
                        "WaveImageURI": "https:\/\/scweb.cwa.gov.tw\/webdata\/drawTrace\/outcome\/2025\/2025077\/1-WSF.gif"
                    },
                    {
                        "StationName": "土庫",
                        "StationID": "WTK",
                        "BackAzimuth": 67.56,
                        "EpicenterDistance": 137.87,
                        "SeismicIntensity": "1級",
                        "StationLatitude": 23.688,
                        "StationLongitude": 120.389
                    },
                    {
                        "pga": {
                            "unit": "gal",
                            "EWComponent": 0.74,
                            "NSComponent": 0.94,
                            "VComponent": 0.4,
                            "IntScaleValue": 0.97
                        },
                        "pgv": {
                            "unit": "kine",
                            "EWComponent": 0.07,
                            "NSComponent": 0.03,
                            "VComponent": 0.02,
                            "IntScaleValue": 0.07
                        },
                        "StationName": "水林",
                        "StationID": "WSL",
                        "InfoStatus": "observe",
                        "BackAzimuth": 63.75,
                        "EpicenterDistance": 160.42,
                        "SeismicIntensity": "1級",
                        "StationLatitude": 23.523,
                        "StationLongitude": 120.228,
                        "WaveImageURI": "https:\/\/scweb.cwa.gov.tw\/webdata\/drawTrace\/outcome\/2025\/2025077\/1-WSL.gif"
                    }
                ]
            },
            {
                "AreaDesc": "新北市地區",
                "CountyName": "新北市",
                "InfoStatus": "observe",
                "AreaIntensity": "1級",
                "EqStation": [
                    {
                        "pga": {
                            "unit": "gal",
                            "EWComponent": 1.9,
                            "NSComponent": 1.62,
                            "VComponent": 1.03,
                            "IntScaleValue": 2.01
                        },
                        "pgv": {
                            "unit": "kine",
                            "EWComponent": 0.09,
                            "NSComponent": 0.08,
                            "VComponent": 0.03,
                            "IntScaleValue": 0.09
                        },
                        "StationName": "新店",
                        "StationID": "NHDH",
                        "InfoStatus": "observe",
                        "BackAzimuth": 172.49,
                        "EpicenterDistance": 89.27,
                        "SeismicIntensity": "1級",
                        "StationLatitude": 24.96,
                        "StationLongitude": 121.525,
                        "WaveImageURI": "https:\/\/scweb.cwa.gov.tw\/webdata\/drawTrace\/outcome\/2025\/2025077\/1-NHDH.gif"
                    },
                    {
                        "pga": {
                            "unit": "gal",
                            "EWComponent": 0.64,
                            "NSComponent": 0.97,
                            "VComponent": 0.55,
                            "IntScaleValue": 0.87
                        },
                        "pgv": {
                            "unit": "kine",
                            "EWComponent": 0.03,
                            "NSComponent": 0.04,
                            "VComponent": 0.02,
                            "IntScaleValue": 0.05
                        },
                        "StationName": "三峽",
                        "StationID": "NSX",
                        "InfoStatus": "observe",
                        "BackAzimuth": 162.64,
                        "EpicenterDistance": 90.35,
                        "SeismicIntensity": "1級",
                        "StationLatitude": 24.939,
                        "StationLongitude": 121.374,
                        "WaveImageURI": "https:\/\/scweb.cwa.gov.tw\/webdata\/drawTrace\/outcome\/2025\/2025077\/1-NSX.gif"
                    },
                    {
                        "pga": {
                            "unit": "gal",
                            "EWComponent": 1.5,
                            "NSComponent": 1.2,
                            "VComponent": 0.88,
                            "IntScaleValue": 1.67
                        },
                        "pgv": {
                            "unit": "kine",
                            "EWComponent": 0.11,
                            "NSComponent": 0.08,
                            "VComponent": 0.04,
                            "IntScaleValue": 0.12
                        },
                        "StationName": "新北市",
                        "StationID": "A024",
                        "InfoStatus": "observe",
                        "BackAzimuth": 170,
                        "EpicenterDistance": 96.59,
                        "SeismicIntensity": "1級",
                        "StationLatitude": 25.019,
                        "StationLongitude": 121.475,
                        "WaveImageURI": "https:\/\/scweb.cwa.gov.tw\/webdata\/drawTrace\/outcome\/2025\/2025077\/1-A024.gif"
                    },
                    {
                        "pga": {
                            "unit": "gal",
                            "EWComponent": 1.96,
                            "NSComponent": 1.82,
                            "VComponent": 0.69,
                            "IntScaleValue": 2.18
                        },
                        "pgv": {
                            "unit": "kine",
                            "EWComponent": 0.07,
                            "NSComponent": 0.06,
                            "VComponent": 0.02,
                            "IntScaleValue": 0.07
                        },
                        "StationName": "汐止",
                        "StationID": "NXZ",
                        "InfoStatus": "observe",
                        "BackAzimuth": 180,
                        "EpicenterDistance": 101.48,
                        "SeismicIntensity": "1級",
                        "StationLatitude": 25.077,
                        "StationLongitude": 121.64,
                        "WaveImageURI": "https:\/\/scweb.cwa.gov.tw\/webdata\/drawTrace\/outcome\/2025\/2025077\/1-NXZ.gif"
                    },
                    {
                        "pga": {
                            "unit": "gal",
                            "EWComponent": 1.25,
                            "NSComponent": 1.71,
                            "VComponent": 0.45,
                            "IntScaleValue": 1.86
                        },
                        "pgv": {
                            "unit": "kine",
                            "EWComponent": 0.09,
                            "NSComponent": 0.14,
                            "VComponent": 0.03,
                            "IntScaleValue": 0.14
                        },
                        "StationName": "五分山",
                        "StationID": "NWF",
                        "InfoStatus": "observe",
                        "BackAzimuth": 188.08,
                        "EpicenterDistance": 101.95,
                        "SeismicIntensity": "1級",
                        "StationLatitude": 25.072,
                        "StationLongitude": 121.782,
                        "WaveImageURI": "https:\/\/scweb.cwa.gov.tw\/webdata\/drawTrace\/outcome\/2025\/2025077\/1-NWF.gif"
                    },
                    {
                        "pga": {
                            "unit": "gal",
                            "EWComponent": 0.75,
                            "NSComponent": 1.01,
                            "VComponent": 0.39,
                            "IntScaleValue": 0.93
                        },
                        "pgv": {
                            "unit": "kine",
                            "EWComponent": 0.03,
                            "NSComponent": 0.05,
                            "VComponent": 0.02,
                            "IntScaleValue": 0.05
                        },
                        "StationName": "淡水",
                        "StationID": "NTS",
                        "InfoStatus": "observe",
                        "BackAzimuth": 170.13,
                        "EpicenterDistance": 112.91,
                        "SeismicIntensity": "1級",
                        "StationLatitude": 25.164,
                        "StationLongitude": 121.449,
                        "WaveImageURI": "https:\/\/scweb.cwa.gov.tw\/webdata\/drawTrace\/outcome\/2025\/2025077\/1-NTS.gif"
                    }
                ]
            },
            {
                "AreaDesc": "最大震度1級地區",
                "CountyName": "新竹縣、苗栗縣、桃園市、新北市、臺東縣、臺北市、雲林縣、嘉義縣",
                "AreaIntensity": "1級",
                "EqStation": []
            },
            {
                "AreaDesc": "花蓮縣地區",
                "CountyName": "花蓮縣",
                "InfoStatus": "observe",
                "AreaIntensity": "3級",
                "EqStation": [
                    {
                        "pga": {
                            "unit": "gal",
                            "EWComponent": 14.1,
                            "NSComponent": 18.59,
                            "VComponent": 5.53,
                            "IntScaleValue": 14.7
                        },
                        "pgv": {
                            "unit": "kine",
                            "EWComponent": 0.29,
                            "NSComponent": 0.4,
                            "VComponent": 0.1,
                            "IntScaleValue": 0.43
                        },
                        "StationName": "太魯閣",
                        "StationID": "ETL",
                        "InfoStatus": "observe",
                        "BackAzimuth": 78.32,
                        "EpicenterDistance": 1.81,
                        "SeismicIntensity": "3級",
                        "StationLatitude": 24.159,
                        "StationLongitude": 121.623,
                        "WaveImageURI": "https:\/\/scweb.cwa.gov.tw\/webdata\/drawTrace\/outcome\/2025\/2025077\/3-ETL.gif"
                    },
                    {
                        "pga": {
                            "unit": "gal",
                            "EWComponent": 16.64,
                            "NSComponent": 14.07,
                            "VComponent": 12.34,
                            "IntScaleValue": 15.03
                        },
                        "pgv": {
                            "unit": "kine",
                            "EWComponent": 0.42,
                            "NSComponent": 0.44,
                            "VComponent": 0.23,
                            "IntScaleValue": 0.47
                        },
                        "StationName": "西寶",
                        "StationID": "ETLH",
                        "InfoStatus": "observe",
                        "BackAzimuth": 107.15,
                        "EpicenterDistance": 16.86,
                        "SeismicIntensity": "3級",
                        "StationLatitude": 24.207,
                        "StationLongitude": 121.482,
                        "WaveImageURI": "https:\/\/scweb.cwa.gov.tw\/webdata\/drawTrace\/outcome\/2025\/2025077\/3-ETLH.gif"
                    },
                    {
                        "pga": {
                            "unit": "gal",
                            "EWComponent": 9.79,
                            "NSComponent": 8.78,
                            "VComponent": 8.55,
                            "IntScaleValue": 8.97
                        },
                        "pgv": {
                            "unit": "kine",
                            "EWComponent": 0.24,
                            "NSComponent": 0.33,
                            "VComponent": 0.22,
                            "IntScaleValue": 0.37
                        },
                        "StationName": "和平",
                        "StationID": "EHP",
                        "InfoStatus": "observe",
                        "BackAzimuth": 214.18,
                        "EpicenterDistance": 19.72,
                        "SeismicIntensity": "3級",
                        "StationLatitude": 24.309,
                        "StationLongitude": 121.749,
                        "WaveImageURI": "https:\/\/scweb.cwa.gov.tw\/webdata\/drawTrace\/outcome\/2025\/2025077\/3-EHP.gif"
                    },
                    {
                        "pga": {
                            "unit": "gal",
                            "EWComponent": 6.39,
                            "NSComponent": 8.83,
                            "VComponent": 2.96,
                            "IntScaleValue": 8.34
                        },
                        "pgv": {
                            "unit": "kine",
                            "EWComponent": 0.3,
                            "NSComponent": 0.43,
                            "VComponent": 0.13,
                            "IntScaleValue": 0.45
                        },
                        "StationName": "花蓮市",
                        "StationID": "HWA",
                        "InfoStatus": "observe",
                        "BackAzimuth": 7.41,
                        "EpicenterDistance": 20.91,
                        "SeismicIntensity": "3級",
                        "StationLatitude": 23.975,
                        "StationLongitude": 121.614,
                        "WaveImageURI": "https:\/\/scweb.cwa.gov.tw\/webdata\/drawTrace\/outcome\/2025\/2025077\/3-HWA.gif"
                    },
                    {
                        "pga": {
                            "unit": "gal",
                            "EWComponent": 11.72,
                            "NSComponent": 12.28,
                            "VComponent": 13.09,
                            "IntScaleValue": 9.68
                        },
                        "pgv": {
                            "unit": "kine",
                            "EWComponent": 0.27,
                            "NSComponent": 0.24,
                            "VComponent": 0.21,
                            "IntScaleValue": 0.32
                        },
                        "StationName": "銅門",
                        "StationID": "ETM",
                        "InfoStatus": "observe",
                        "BackAzimuth": 34.59,
                        "EpicenterDistance": 26.43,
                        "SeismicIntensity": "3級",
                        "StationLatitude": 23.966,
                        "StationLongitude": 121.493,
                        "WaveImageURI": "https:\/\/scweb.cwa.gov.tw\/webdata\/drawTrace\/outcome\/2025\/2025077\/3-ETM.gif"
                    },
                    {
                        "pga": {
                            "unit": "gal",
                            "EWComponent": 10.42,
                            "NSComponent": 16.61,
                            "VComponent": 10.81,
                            "IntScaleValue": 16.1
                        },
                        "pgv": {
                            "unit": "kine",
                            "EWComponent": 0.55,
                            "NSComponent": 0.63,
                            "VComponent": 0.22,
                            "IntScaleValue": 0.74
                        },
                        "StationName": "鹽寮",
                        "StationID": "EYL",
                        "InfoStatus": "observe",
                        "BackAzimuth": 7.8,
                        "EpicenterDistance": 28.95,
                        "SeismicIntensity": "3級",
                        "StationLatitude": 23.904,
                        "StationLongitude": 121.602,
                        "WaveImageURI": "https:\/\/scweb.cwa.gov.tw\/webdata\/drawTrace\/outcome\/2025\/2025077\/3-EYL.gif"
                    },
                    {
                        "pga": {
                            "unit": "gal",
                            "EWComponent": 4.08,
                            "NSComponent": 5.24,
                            "VComponent": 6.06,
                            "IntScaleValue": 5.07
                        },
                        "pgv": {
                            "unit": "kine",
                            "EWComponent": 0.14,
                            "NSComponent": 0.15,
                            "VComponent": 0.11,
                            "IntScaleValue": 0.17
                        },
                        "StationName": "秀林",
                        "StationID": "TWD",
                        "InfoStatus": "observe",
                        "BackAzimuth": 22.11,
                        "EpicenterDistance": 9.68,
                        "SeismicIntensity": "2級",
                        "StationLatitude": 24.081,
                        "StationLongitude": 121.605,
                        "WaveImageURI": "https:\/\/scweb.cwa.gov.tw\/webdata\/drawTrace\/outcome\/2025\/2025077\/2-TWD.gif"
                    },
                    {
                        "pga": {
                            "unit": "gal",
                            "EWComponent": 8.63,
                            "NSComponent": 8.99,
                            "VComponent": 2.88,
                            "IntScaleValue": 3.49
                        },
                        "pgv": {
                            "unit": "kine",
                            "EWComponent": 0.1,
                            "NSComponent": 0.1,
                            "VComponent": 0.04,
                            "IntScaleValue": 0.1
                        },
                        "StationName": "西林",
                        "StationID": "ESL",
                        "InfoStatus": "observe",
                        "BackAzimuth": 27.51,
                        "EpicenterDistance": 43.78,
                        "SeismicIntensity": "2級",
                        "StationLatitude": 23.812,
                        "StationLongitude": 121.442,
                        "WaveImageURI": "https:\/\/scweb.cwa.gov.tw\/webdata\/drawTrace\/outcome\/2025\/2025077\/2-ESL.gif"
                    },
                    {
                        "pga": {
                            "unit": "gal",
                            "EWComponent": 3.88,
                            "NSComponent": 3.54,
                            "VComponent": 1.23,
                            "IntScaleValue": 4.06
                        },
                        "pgv": {
                            "unit": "kine",
                            "EWComponent": 0.12,
                            "NSComponent": 0.11,
                            "VComponent": 0.03,
                            "IntScaleValue": 0.12
                        },
                        "StationName": "磯崎",
                        "StationID": "EGC",
                        "InfoStatus": "observe",
                        "BackAzimuth": 10.61,
                        "EpicenterDistance": 51.27,
                        "SeismicIntensity": "2級",
                        "StationLatitude": 23.708,
                        "StationLongitude": 121.548,
                        "WaveImageURI": "https:\/\/scweb.cwa.gov.tw\/webdata\/drawTrace\/outcome\/2025\/2025077\/2-EGC.gif"
                    },
                    {
                        "pga": {
                            "unit": "gal",
                            "EWComponent": 3.55,
                            "NSComponent": 2.59,
                            "VComponent": 2.91,
                            "IntScaleValue": 3.21
                        },
                        "pgv": {
                            "unit": "kine",
                            "EWComponent": 0.08,
                            "NSComponent": 0.06,
                            "VComponent": 0.04,
                            "IntScaleValue": 0.08
                        },
                        "StationName": "光復",
                        "StationID": "EGFH",
                        "InfoStatus": "observe",
                        "BackAzimuth": 21.61,
                        "EpicenterDistance": 58.85,
                        "SeismicIntensity": "2級",
                        "StationLatitude": 23.669,
                        "StationLongitude": 121.428,
                        "WaveImageURI": "https:\/\/scweb.cwa.gov.tw\/webdata\/drawTrace\/outcome\/2025\/2025077\/2-EGFH.gif"
                    },
                    {
                        "pga": {
                            "unit": "gal",
                            "EWComponent": 1.46,
                            "NSComponent": 1.34,
                            "VComponent": 0.74,
                            "IntScaleValue": 0.94
                        },
                        "pgv": {
                            "unit": "kine",
                            "EWComponent": 0.02,
                            "NSComponent": 0.03,
                            "VComponent": 0.02,
                            "IntScaleValue": 0.03
                        },
                        "StationName": "紅葉",
                        "StationID": "EHY",
                        "InfoStatus": "observe",
                        "BackAzimuth": 23.41,
                        "EpicenterDistance": 79.58,
                        "SeismicIntensity": "1級",
                        "StationLatitude": 23.504,
                        "StationLongitude": 121.33,
                        "WaveImageURI": "https:\/\/scweb.cwa.gov.tw\/webdata\/drawTrace\/outcome\/2025\/2025077\/1-EHY.gif"
                    }
                ]
            },
            {
                "AreaDesc": "苗栗縣地區",
                "CountyName": "苗栗縣",
                "InfoStatus": "observe",
                "AreaIntensity": "1級",
                "EqStation": [
                    {
                        "pga": {
                            "unit": "gal",
                            "EWComponent": 0.93,
                            "NSComponent": 1.2,
                            "VComponent": 0.81,
                            "IntScaleValue": 1.26
                        },
                        "pgv": {
                            "unit": "kine",
                            "EWComponent": 0.06,
                            "NSComponent": 0.07,
                            "VComponent": 0.05,
                            "IntScaleValue": 0.07
                        },
                        "StationName": "泰安",
                        "StationID": "H176",
                        "InfoStatus": "observe",
                        "BackAzimuth": 115.36,
                        "EpicenterDistance": 78.59,
                        "SeismicIntensity": "1級",
                        "StationLatitude": 24.465,
                        "StationLongitude": 120.941,
                        "WaveImageURI": "https:\/\/scweb.cwa.gov.tw\/webdata\/drawTrace\/outcome\/2025\/2025077\/1-H176.gif"
                    },
                    {
                        "pga": {
                            "unit": "gal",
                            "EWComponent": 1.36,
                            "NSComponent": 1.23,
                            "VComponent": 0.55,
                            "IntScaleValue": 1.39
                        },
                        "pgv": {
                            "unit": "kine",
                            "EWComponent": 0.1,
                            "NSComponent": 0.09,
                            "VComponent": 0.05,
                            "IntScaleValue": 0.1
                        },
                        "StationName": "南庄",
                        "StationID": "NST",
                        "InfoStatus": "observe",
                        "BackAzimuth": 129.01,
                        "EpicenterDistance": 82.43,
                        "SeismicIntensity": "1級",
                        "StationLatitude": 24.63,
                        "StationLongitude": 121.009,
                        "WaveImageURI": "https:\/\/scweb.cwa.gov.tw\/webdata\/drawTrace\/outcome\/2025\/2025077\/1-NST.gif"
                    },
                    {
                        "pga": {
                            "unit": "gal",
                            "EWComponent": 0.67,
                            "NSComponent": 0.73,
                            "VComponent": 0.39,
                            "IntScaleValue": 0.94
                        },
                        "pgv": {
                            "unit": "kine",
                            "EWComponent": 0.04,
                            "NSComponent": 0.06,
                            "VComponent": 0.03,
                            "IntScaleValue": 0.06
                        },
                        "StationName": "鯉魚潭",
                        "StationID": "TWQ1",
                        "InfoStatus": "observe",
                        "BackAzimuth": 103.2,
                        "EpicenterDistance": 89.64,
                        "SeismicIntensity": "1級",
                        "StationLatitude": 24.347,
                        "StationLongitude": 120.781,
                        "WaveImageURI": "https:\/\/scweb.cwa.gov.tw\/webdata\/drawTrace\/outcome\/2025\/2025077\/1-TWQ1.gif"
                    },
                    {
                        "pga": {
                            "unit": "gal",
                            "EWComponent": 0.89,
                            "NSComponent": 0.53,
                            "VComponent": 0.85,
                            "IntScaleValue": 0.9
                        },
                        "pgv": {
                            "unit": "kine",
                            "EWComponent": 0.07,
                            "NSComponent": 0.05,
                            "VComponent": 0.03,
                            "IntScaleValue": 0.07
                        },
                        "StationName": "三義",
                        "StationID": "NSY",
                        "InfoStatus": "observe",
                        "BackAzimuth": 107.58,
                        "EpicenterDistance": 92.71,
                        "SeismicIntensity": "1級",
                        "StationLatitude": 24.414,
                        "StationLongitude": 120.77,
                        "WaveImageURI": "https:\/\/scweb.cwa.gov.tw\/webdata\/drawTrace\/outcome\/2025\/2025077\/1-NSY.gif"
                    },
                    {
                        "pga": {
                            "unit": "gal",
                            "EWComponent": 0.7,
                            "NSComponent": 0.79,
                            "VComponent": 0.4,
                            "IntScaleValue": 0.83
                        },
                        "pgv": {
                            "unit": "kine",
                            "EWComponent": 0.06,
                            "NSComponent": 0.06,
                            "VComponent": 0.02,
                            "IntScaleValue": 0.07
                        },
                        "StationName": "苗栗市",
                        "StationID": "NML",
                        "InfoStatus": "observe",
                        "BackAzimuth": 118.41,
                        "EpicenterDistance": 93.96,
                        "SeismicIntensity": "1級",
                        "StationLatitude": 24.565,
                        "StationLongitude": 120.826,
                        "WaveImageURI": "https:\/\/scweb.cwa.gov.tw\/webdata\/drawTrace\/outcome\/2025\/2025077\/1-NML.gif"
                    },
                    {
                        "pga": {
                            "unit": "gal",
                            "EWComponent": 1.19,
                            "NSComponent": 1.66,
                            "VComponent": 1.03,
                            "IntScaleValue": 1.9
                        },
                        "pgv": {
                            "unit": "kine",
                            "EWComponent": 0.09,
                            "NSComponent": 0.11,
                            "VComponent": 0.03,
                            "IntScaleValue": 0.12
                        },
                        "StationName": "竹南",
                        "StationID": "NJN",
                        "InfoStatus": "observe",
                        "BackAzimuth": 126.55,
                        "EpicenterDistance": 97.2,
                        "SeismicIntensity": "1級",
                        "StationLatitude": 24.684,
                        "StationLongitude": 120.87,
                        "WaveImageURI": "https:\/\/scweb.cwa.gov.tw\/webdata\/drawTrace\/outcome\/2025\/2025077\/1-NJN.gif"
                    }
                ]
            },
            {
                "AreaDesc": "最大震度2級地區",
                "CountyName": "臺中市、彰化縣",
                "AreaIntensity": "2級",
                "EqStation": []
            },
            {
                "AreaDesc": "臺東縣地區",
                "CountyName": "臺東縣",
                "InfoStatus": "observe",
                "AreaIntensity": "1級",
                "EqStation": [
                    {
                        "pga": {
                            "unit": "gal",
                            "EWComponent": 0.86,
                            "NSComponent": 0.91,
                            "VComponent": 0.35,
                            "IntScaleValue": 0.81
                        },
                        "pgv": {
                            "unit": "kine",
                            "EWComponent": 0.07,
                            "NSComponent": 0.03,
                            "VComponent": 0.01,
                            "IntScaleValue": 0.07
                        },
                        "StationName": "長濱",
                        "StationID": "ECB",
                        "InfoStatus": "observe",
                        "BackAzimuth": 11.61,
                        "EpicenterDistance": 95.78,
                        "SeismicIntensity": "1級",
                        "StationLatitude": 23.316,
                        "StationLongitude": 121.451,
                        "WaveImageURI": "https:\/\/scweb.cwa.gov.tw\/webdata\/drawTrace\/outcome\/2025\/2025077\/1-ECB.gif"
                    },
                    {
                        "pga": {
                            "unit": "gal",
                            "EWComponent": 1.35,
                            "NSComponent": 1.02,
                            "VComponent": 0.36,
                            "IntScaleValue": 1.07
                        },
                        "pgv": {
                            "unit": "kine",
                            "EWComponent": 0.03,
                            "NSComponent": 0.02,
                            "VComponent": 0.01,
                            "IntScaleValue": 0.04
                        },
                        "StationName": "成功",
                        "StationID": "CHK",
                        "InfoStatus": "observe",
                        "BackAzimuth": 13,
                        "EpicenterDistance": 121.18,
                        "SeismicIntensity": "1級",
                        "StationLatitude": 23.098,
                        "StationLongitude": 121.373,
                        "WaveImageURI": "https:\/\/scweb.cwa.gov.tw\/webdata\/drawTrace\/outcome\/2025\/2025077\/1-CHK.gif"
                    },
                    {
                        "StationName": "池上",
                        "StationID": "ECS",
                        "BackAzimuth": 19.95,
                        "EpicenterDistance": 125.92,
                        "SeismicIntensity": "1級",
                        "StationLatitude": 23.095,
                        "StationLongitude": 121.219
                    }
                ]
            },
            {
                "AreaDesc": "彰化縣地區",
                "CountyName": "彰化縣",
                "InfoStatus": "observe",
                "AreaIntensity": "2級",
                "EqStation": [
                    {
                        "pga": {
                            "unit": "gal",
                            "EWComponent": 3.95,
                            "NSComponent": 3.56,
                            "VComponent": 1.51,
                            "IntScaleValue": 3.65
                        },
                        "pgv": {
                            "unit": "kine",
                            "EWComponent": 0.09,
                            "NSComponent": 0.09,
                            "VComponent": 0.04,
                            "IntScaleValue": 0.1
                        },
                        "StationName": "彰化市",
                        "StationID": "WCHH",
                        "InfoStatus": "observe",
                        "BackAzimuth": 85.24,
                        "EpicenterDistance": 110.37,
                        "SeismicIntensity": "2級",
                        "StationLatitude": 24.079,
                        "StationLongitude": 120.558,
                        "WaveImageURI": "https:\/\/scweb.cwa.gov.tw\/webdata\/drawTrace\/outcome\/2025\/2025077\/2-WCHH.gif"
                    },
                    {
                        "pga": {
                            "unit": "gal",
                            "EWComponent": 2.26,
                            "NSComponent": 1.67,
                            "VComponent": 1.32,
                            "IntScaleValue": 2.17
                        },
                        "pgv": {
                            "unit": "kine",
                            "EWComponent": 0.08,
                            "NSComponent": 0.08,
                            "VComponent": 0.04,
                            "IntScaleValue": 0.1
                        },
                        "StationName": "員林",
                        "StationID": "WYL",
                        "InfoStatus": "observe",
                        "BackAzimuth": 78.29,
                        "EpicenterDistance": 110.13,
                        "SeismicIntensity": "1級",
                        "StationLatitude": 23.961,
                        "StationLongitude": 120.58,
                        "WaveImageURI": "https:\/\/scweb.cwa.gov.tw\/webdata\/drawTrace\/outcome\/2025\/2025077\/1-WYL.gif"
                    },
                    {
                        "pga": {
                            "unit": "gal",
                            "EWComponent": 1.48,
                            "NSComponent": 1.05,
                            "VComponent": 0.79,
                            "IntScaleValue": 1.43
                        },
                        "pgv": {
                            "unit": "kine",
                            "EWComponent": 0.05,
                            "NSComponent": 0.05,
                            "VComponent": 0.03,
                            "IntScaleValue": 0.05
                        },
                        "StationName": "鹿港",
                        "StationID": "B112",
                        "InfoStatus": "observe",
                        "BackAzimuth": 84.5,
                        "EpicenterDistance": 123.58,
                        "SeismicIntensity": "1級",
                        "StationLatitude": 24.055,
                        "StationLongitude": 120.43,
                        "WaveImageURI": "https:\/\/scweb.cwa.gov.tw\/webdata\/drawTrace\/outcome\/2025\/2025077\/1-B112.gif"
                    },
                    {
                        "pga": {
                            "unit": "gal",
                            "EWComponent": 1.26,
                            "NSComponent": 1.16,
                            "VComponent": 0.55,
                            "IntScaleValue": 1.33
                        },
                        "pgv": {
                            "unit": "kine",
                            "EWComponent": 0.04,
                            "NSComponent": 0.04,
                            "VComponent": 0.02,
                            "IntScaleValue": 0.05
                        },
                        "StationName": "大城",
                        "StationID": "WTC",
                        "InfoStatus": "observe",
                        "BackAzimuth": 76.37,
                        "EpicenterDistance": 141.43,
                        "SeismicIntensity": "1級",
                        "StationLatitude": 23.862,
                        "StationLongitude": 120.289,
                        "WaveImageURI": "https:\/\/scweb.cwa.gov.tw\/webdata\/drawTrace\/outcome\/2025\/2025077\/1-WTC.gif"
                    },
                    {
                        "pga": {
                            "unit": "gal",
                            "EWComponent": 1.77,
                            "NSComponent": 1.66,
                            "VComponent": 1.33,
                            "IntScaleValue": 1.65
                        },
                        "pgv": {
                            "unit": "kine",
                            "EWComponent": 0.05,
                            "NSComponent": 0.07,
                            "VComponent": 0.03,
                            "IntScaleValue": 0.07
                        },
                        "StationName": "二林",
                        "StationID": "WRL",
                        "InfoStatus": "observe",
                        "BackAzimuth": 77.36,
                        "EpicenterDistance": 131.57,
                        "SeismicIntensity": "1級",
                        "StationLatitude": 23.903,
                        "StationLongitude": 120.378,
                        "WaveImageURI": "https:\/\/scweb.cwa.gov.tw\/webdata\/drawTrace\/outcome\/2025\/2025077\/1-WRL.gif"
                    }
                ]
            },
            {
                "AreaDesc": "桃園市地區",
                "CountyName": "桃園市",
                "InfoStatus": "observe",
                "AreaIntensity": "1級",
                "EqStation": [
                    {
                        "pga": {
                            "unit": "gal",
                            "EWComponent": 1.29,
                            "NSComponent": 1.37,
                            "VComponent": 0.59,
                            "IntScaleValue": 1.54
                        },
                        "pgv": {
                            "unit": "kine",
                            "EWComponent": 0.06,
                            "NSComponent": 0.07,
                            "VComponent": 0.03,
                            "IntScaleValue": 0.07
                        },
                        "StationName": "大溪",
                        "StationID": "B011",
                        "InfoStatus": "observe",
                        "BackAzimuth": 155.89,
                        "EpicenterDistance": 87.8,
                        "SeismicIntensity": "1級",
                        "StationLatitude": 24.884,
                        "StationLongitude": 121.286,
                        "WaveImageURI": "https:\/\/scweb.cwa.gov.tw\/webdata\/drawTrace\/outcome\/2025\/2025077\/1-B011.gif"
                    },
                    {
                        "pga": {
                            "unit": "gal",
                            "EWComponent": 2.08,
                            "NSComponent": 1.63,
                            "VComponent": 0.78,
                            "IntScaleValue": 1.92
                        },
                        "pgv": {
                            "unit": "kine",
                            "EWComponent": 0.09,
                            "NSComponent": 0.06,
                            "VComponent": 0.03,
                            "IntScaleValue": 0.1
                        },
                        "StationName": "桃園市",
                        "StationID": "NTY",
                        "InfoStatus": "observe",
                        "BackAzimuth": 159.52,
                        "EpicenterDistance": 99.23,
                        "SeismicIntensity": "1級",
                        "StationLatitude": 25,
                        "StationLongitude": 121.298,
                        "WaveImageURI": "https:\/\/scweb.cwa.gov.tw\/webdata\/drawTrace\/outcome\/2025\/2025077\/1-NTY.gif"
                    },
                    {
                        "pga": {
                            "unit": "gal",
                            "EWComponent": 0.91,
                            "NSComponent": 0.55,
                            "VComponent": 0.53,
                            "IntScaleValue": 1.05
                        },
                        "pgv": {
                            "unit": "kine",
                            "EWComponent": 0.09,
                            "NSComponent": 0.03,
                            "VComponent": 0.03,
                            "IntScaleValue": 0.09
                        },
                        "StationName": "中壢",
                        "StationID": "NCU",
                        "InfoStatus": "observe",
                        "BackAzimuth": 152.79,
                        "EpicenterDistance": 100.46,
                        "SeismicIntensity": "1級",
                        "StationLatitude": 24.967,
                        "StationLongitude": 121.187,
                        "WaveImageURI": "https:\/\/scweb.cwa.gov.tw\/webdata\/drawTrace\/outcome\/2025\/2025077\/1-NCU.gif"
                    },
                    {
                        "pga": {
                            "unit": "gal",
                            "EWComponent": 0.9,
                            "NSComponent": 1.06,
                            "VComponent": 0.23,
                            "IntScaleValue": 0.98
                        },
                        "pgv": {
                            "unit": "kine",
                            "EWComponent": 0.04,
                            "NSComponent": 0.03,
                            "VComponent": 0.01,
                            "IntScaleValue": 0.04
                        },
                        "StationName": "新屋",
                        "StationID": "NHW",
                        "InfoStatus": "observe",
                        "BackAzimuth": 147.36,
                        "EpicenterDistance": 111.31,
                        "SeismicIntensity": "1級",
                        "StationLatitude": 25.007,
                        "StationLongitude": 121.048,
                        "WaveImageURI": "https:\/\/scweb.cwa.gov.tw\/webdata\/drawTrace\/outcome\/2025\/2025077\/1-NHW.gif"
                    },
                    {
                        "pga": {
                            "unit": "gal",
                            "EWComponent": 1.72,
                            "NSComponent": 2.39,
                            "VComponent": 0.84,
                            "IntScaleValue": 2.27
                        },
                        "pgv": {
                            "unit": "kine",
                            "EWComponent": 0.07,
                            "NSComponent": 0.11,
                            "VComponent": 0.05,
                            "IntScaleValue": 0.11
                        },
                        "StationName": "三光",
                        "StationID": "NSK",
                        "InfoStatus": "observe",
                        "BackAzimuth": 153.95,
                        "EpicenterDistance": 63.2,
                        "SeismicIntensity": "1級",
                        "StationLatitude": 24.674,
                        "StationLongitude": 121.367,
                        "WaveImageURI": "https:\/\/scweb.cwa.gov.tw\/webdata\/drawTrace\/outcome\/2025\/2025077\/1-NSK.gif"
                    }
                ]
            },
            {
                "AreaDesc": "新竹縣地區",
                "CountyName": "新竹縣",
                "InfoStatus": "observe",
                "AreaIntensity": "1級",
                "EqStation": []
            },
            {
                "AreaDesc": "臺中市地區",
                "CountyName": "臺中市",
                "InfoStatus": "observe",
                "AreaIntensity": "2級",
                "EqStation": []
            },
            {
                "AreaDesc": "最大震度3級地區",
                "CountyName": "花蓮縣、宜蘭縣、南投縣",
                "AreaIntensity": "3級",
                "EqStation": []
            },
            {
                "AreaDesc": "嘉義縣地區",
                "CountyName": "嘉義縣",
                "InfoStatus": "observe",
                "AreaIntensity": "1級",
                "EqStation": []
            },
            {
                "AreaDesc": "宜蘭縣地區",
                "CountyName": "宜蘭縣",
                "InfoStatus": "observe",
                "AreaIntensity": "3級",
                "EqStation": []
            }
        ]
    }
}