{
    "EarthquakeNo": 113310,
    "ReportType": "地震報告",
    "ReportColor": "綠色",
    "ReportContent": "04\/23-08:11花蓮縣近海發生規模5.1有感地震，最大震度花蓮縣鹽寮、花蓮縣花蓮市4級。",
    "ReportImageURI": "https:\/\/scweb.cwa.gov.tw\/webdata\/OLDEQ\/202404\/2024042308110251310_H.png",
    "ReportRemark": "本報告係中央氣象署地震觀測網即時地震資料地震速報之結果。",
    "Web": "https:\/\/scweb.cwa.gov.tw\/zh-tw\/earthquake\/details\/2024042308110251310",
    "ShakemapImageURI": "https:\/\/scweb.cwa.gov.tw\/webdata\/drawTrace\/plotContour\/2024\/2024310i.png",
    "EarthquakeInfo": {
        "OriginTime": "2024-04-23 08:11:02",
        "Source": "中央氣象署",
        "FocalDepth": 9,
        "Epicenter": {
            "Location": "花蓮縣政府南方  9.4  公里 (位於花蓮縣近海)",
            "EpicenterLatitude": 23.91,
            "EpicenterLongitude": 121.6
        },
        "EarthquakeMagnitude": {
            "MagnitudeType": "芮氏規模",
            "MagnitudeValue": 5.1
        }
    },
    "Intensity": {
        "ShakingArea": [
            {
                "AreaDesc": "桃園市地區",
                "CountyName": "桃園市",
                "InfoStatus": "observe",
                "AreaIntensity": "2級",
                "EqStation": [
                    {
                        "pga": {
                            "unit": "gal",
                            "EWComponent": 1.78,
                            "NSComponent": 2.05,
                            "VComponent": 0.79,
                            "IntScaleValue": 2.14
                        },
                        "pgv": {
                            "unit": "kine",
                            "EWComponent": 0.13,
                            "NSComponent": 0.24,
                            "VComponent": 0.11,
                            "IntScaleValue": 0.24
                        },
                        "StationName": "中壢",
                        "StationID": "NCU",
                        "InfoStatus": "observe",
                        "BackAzimuth": 160.19,
                        "EpicenterDistance": 125.03,
                        "SeismicIntensity": "1級",
                        "StationLatitude": 24.967,
                        "StationLongitude": 121.187,
                        "WaveImageURI": "https:\/\/scweb.cwa.gov.tw\/webdata\/drawTrace\/outcome\/2024\/2024310\/1-NCU.gif"
                    },
                    {
                        "pga": {
                            "unit": "gal",
                            "EWComponent": 1.79,
                            "NSComponent": 2.1,
                            "VComponent": 0.64,
                            "IntScaleValue": 2.16
                        },
                        "pgv": {
                            "unit": "kine",
                            "EWComponent": 0.12,
                            "NSComponent": 0.13,
                            "VComponent": 0.05,
                            "IntScaleValue": 0.14
                        },
                        "StationName": "桃園市",
                        "StationID": "NTY",
                        "InfoStatus": "observe",
                        "BackAzimuth": 165.59,
                        "EpicenterDistance": 125.19,
                        "SeismicIntensity": "1級",
                        "StationLatitude": 25,
                        "StationLongitude": 121.298,
                        "WaveImageURI": "https:\/\/scweb.cwa.gov.tw\/webdata\/drawTrace\/outcome\/2024\/2024310\/1-NTY.gif"
                    }
                ]
            }
        ]
    }
}